kaikosdk/__init__.py
kaikosdk/sdk_pb2.py
kaikosdk/sdk_pb2_grpc.py
kaikosdk/core/__init__.py
kaikosdk/core/assets_pb2.py
kaikosdk/core/assets_pb2_grpc.py
kaikosdk/core/data_interval_pb2.py
kaikosdk/core/data_interval_pb2_grpc.py
kaikosdk/core/instrument_criteria_pb2.py
kaikosdk/core/instrument_criteria_pb2_grpc.py
kaikosdk/core/sort_criteria_pb2.py
kaikosdk/core/sort_criteria_pb2_grpc.py
kaikosdk/core/source_data_pb2.py
kaikosdk/core/source_data_pb2_grpc.py
kaikosdk/core/source_pb2.py
kaikosdk/core/source_pb2_grpc.py
kaikosdk/core/window_pb2.py
kaikosdk/core/window_pb2_grpc.py
kaikosdk/core/wrappers_pb2.py
kaikosdk/core/wrappers_pb2_grpc.py
kaikosdk/stream/__init__.py
kaikosdk/stream/aggregated_price_v1/__init__.py
kaikosdk/stream/aggregated_price_v1/request_pb2.py
kaikosdk/stream/aggregated_price_v1/request_pb2_grpc.py
kaikosdk/stream/aggregated_price_v1/response_pb2.py
kaikosdk/stream/aggregated_price_v1/response_pb2_grpc.py
kaikosdk/stream/aggregated_quote_v2/__init__.py
kaikosdk/stream/aggregated_quote_v2/request_pb2.py
kaikosdk/stream/aggregated_quote_v2/request_pb2_grpc.py
kaikosdk/stream/aggregated_quote_v2/response_pb2.py
kaikosdk/stream/aggregated_quote_v2/response_pb2_grpc.py
kaikosdk/stream/aggregated_state_price_v1/__init__.py
kaikosdk/stream/aggregated_state_price_v1/request_pb2.py
kaikosdk/stream/aggregated_state_price_v1/request_pb2_grpc.py
kaikosdk/stream/aggregated_state_price_v1/response_pb2.py
kaikosdk/stream/aggregated_state_price_v1/response_pb2_grpc.py
kaikosdk/stream/aggregates_direct_exchange_rate_v2/__init__.py
kaikosdk/stream/aggregates_direct_exchange_rate_v2/request_pb2.py
kaikosdk/stream/aggregates_direct_exchange_rate_v2/request_pb2_grpc.py
kaikosdk/stream/aggregates_direct_exchange_rate_v2/response_pb2.py
kaikosdk/stream/aggregates_direct_exchange_rate_v2/response_pb2_grpc.py
kaikosdk/stream/aggregates_ohlcv_v1/__init__.py
kaikosdk/stream/aggregates_ohlcv_v1/request_pb2.py
kaikosdk/stream/aggregates_ohlcv_v1/request_pb2_grpc.py
kaikosdk-1.29.0.dist-info/METADATA
kaikosdk-1.29.0.dist-info/WHEEL
kaikosdk-1.29.0.dist-info/top_level.txt
kaikosdk-1.29.0.dist-info/RECORD
