Metadata-Version: 2.4
Name: kaikosdk
Version: 1.29.0
Summary: Kaiko SDK
Home-page: https://www.kaiko.com/
Author: Kaiko
Author-email: hello@kaiko.com
License: MIT
Dynamic: author
Dynamic: author-email
Dynamic: home-page
Dynamic: license
Dynamic: summary
